{
  "ComponentIndexes": {},
  "ControlUniqueGuids": {},
  "ControlUniqueIds": {
    "Actief_DataCard1": 309,
    "Actief_DataCard2": 782,
    "Adres_DataCard1": 244,
    "Adres_DataCard2": 737,
    "Adres_DataCard5": 565,
    "Adres_DataCard5_1": 440,
    "Afbetalingen_DataCard2": 195,
    "Afspraken_DataCard4": 605,
    "Afspraken_DataCard4_1": 480,
    "Alimentatieuit_DataCard2": 200,
    "Andere inkomsten_DataCard2": 135,
    "Andere uitgaven_DataCard2": 210,
    "App": 1,
    "Attachments_DataCard3": 350,
    "Bezoeker_DataCard2": 43,
    "Body1": 24,
    "Budgetmeter_DataCard2": 205,
    "Burgerlijke staat_DataCard1": 294,
    "Burgerlijke staat_DataCard2": 787,
    "Button1": 221,
    "Button1_1": 101,
    "Button1_2": 341,
    "Button1_3": 356,
    "Button10": 36,
    "Button11": 35,
    "Button12": 314,
    "Button13": 98,
    "Button13_1": 339,
    "Button14": 393,
    "Button14_1": 394,
    "Button14_2": 431,
    "Button14_3": 432,
    "Button15": 810,
    "Button15_1": 816,
    "Button15_4": 815,
    "Button15_5": 817,
    "Button2": 220,
    "Button2_1": 100,
    "Button2_2": 340,
    "Button2_3": 355,
    "Button3": 714,
    "Button4": 40,
    "Button5": 715,
    "Button6": 26,
    "Button6_1": 14,
    "Button7": 682,
    "Button7_1": 557,
    "Button8": 681,
    "Button8_1": 556,
    "Button9": 39,
    "ContactenScherm": 44,
    "Dakloos_DataCard1": 274,
    "Dakloos_DataCard2": 762,
    "DataCardKey1": 232,
    "DataCardKey10": 277,
    "DataCardKey100": 598,
    "DataCardKey100_1": 473,
    "DataCardKey101": 603,
    "DataCardKey101_1": 478,
    "DataCardKey102": 608,
    "DataCardKey102_1": 483,
    "DataCardKey11": 282,
    "DataCardKey115": 112,
    "DataCardKey116": 117,
    "DataCardKey117": 122,
    "DataCardKey118": 127,
    "DataCardKey119": 132,
    "DataCardKey12": 287,
    "DataCardKey120": 137,
    "DataCardKey122": 142,
    "DataCardKey123": 147,
    "DataCardKey124": 152,
    "DataCardKey125": 157,
    "DataCardKey126": 162,
    "DataCardKey127": 167,
    "DataCardKey128": 172,
    "DataCardKey129": 177,
    "DataCardKey13": 292,
    "DataCardKey130": 182,
    "DataCardKey131": 187,
    "DataCardKey132": 192,
    "DataCardKey133": 197,
    "DataCardKey134": 202,
    "DataCardKey135": 207,
    "DataCardKey136": 212,
    "DataCardKey139": 217,
    "DataCardKey14": 311,
    "DataCardKey15": 297,
    "DataCardKey16": 302,
    "DataCardKey17": 307,
    "DataCardKey18": 494,
    "DataCardKey19": 619,
    "DataCardKey2": 237,
    "DataCardKey20": 54,
    "DataCardKey21": 59,
    "DataCardKey22": 64,
    "DataCardKey23": 69,
    "DataCardKey24": 74,
    "DataCardKey25": 79,
    "DataCardKey26": 84,
    "DataCardKey27": 89,
    "DataCardKey28": 718,
    "DataCardKey29": 723,
    "DataCardKey3": 242,
    "DataCardKey30": 326,
    "DataCardKey31": 336,
    "DataCardKey32": 331,
    "DataCardKey33": 728,
    "DataCardKey34": 733,
    "DataCardKey35": 738,
    "DataCardKey36": 743,
    "DataCardKey37": 748,
    "DataCardKey38": 753,
    "DataCardKey39": 758,
    "DataCardKey4": 262,
    "DataCardKey40": 763,
    "DataCardKey41": 768,
    "DataCardKey42": 773,
    "DataCardKey43": 778,
    "DataCardKey44": 783,
    "DataCardKey45": 788,
    "DataCardKey46": 793,
    "DataCardKey47": 798,
    "DataCardKey48": 803,
    "DataCardKey5": 247,
    "DataCardKey50": 613,
    "DataCardKey50_1": 488,
    "DataCardKey52": 624,
    "DataCardKey52_1": 498,
    "DataCardKey53": 629,
    "DataCardKey53_1": 504,
    "DataCardKey54": 634,
    "DataCardKey54_1": 508,
    "DataCardKey55": 639,
    "DataCardKey55_1": 514,
    "DataCardKey56": 644,
    "DataCardKey56_1": 518,
    "DataCardKey57": 649,
    "DataCardKey57_1": 524,
    "DataCardKey58": 654,
    "DataCardKey58_1": 527,
    "DataCardKey59": 659,
    "DataCardKey59_1": 534,
    "DataCardKey6": 252,
    "DataCardKey60": 664,
    "DataCardKey60_1": 537,
    "DataCardKey61": 669,
    "DataCardKey61_1": 544,
    "DataCardKey62": 674,
    "DataCardKey62_1": 548,
    "DataCardKey63": 679,
    "DataCardKey63_1": 554,
    "DataCardKey67": 365,
    "DataCardKey67_1": 403,
    "DataCardKey7": 257,
    "DataCardKey71": 380,
    "DataCardKey71_1": 418,
    "DataCardKey72": 375,
    "DataCardKey72_1": 413,
    "DataCardKey73": 385,
    "DataCardKey73_1": 423,
    "DataCardKey74": 370,
    "DataCardKey74_1": 408,
    "DataCardKey75": 390,
    "DataCardKey75_1": 428,
    "DataCardKey8": 267,
    "DataCardKey9": 272,
    "DataCardKey90": 352,
    "DataCardKey93": 563,
    "DataCardKey93_1": 438,
    "DataCardKey94": 568,
    "DataCardKey94_1": 443,
    "DataCardKey95": 583,
    "DataCardKey95_1": 458,
    "DataCardKey96": 573,
    "DataCardKey96_1": 448,
    "DataCardKey97": 588,
    "DataCardKey97_1": 463,
    "DataCardKey98": 578,
    "DataCardKey98_1": 453,
    "DataCardKey99": 593,
    "DataCardKey99_1": 468,
    "DataCardValue1": 230,
    "DataCardValue10": 275,
    "DataCardValue100": 596,
    "DataCardValue100_1": 471,
    "DataCardValue101": 601,
    "DataCardValue101_1": 476,
    "DataCardValue102": 606,
    "DataCardValue102_1": 481,
    "DataCardValue11": 280,
    "DataCardValue115": 113,
    "DataCardValue116": 118,
    "DataCardValue117": 123,
    "DataCardValue118": 128,
    "DataCardValue119": 133,
    "DataCardValue12": 285,
    "DataCardValue120": 138,
    "DataCardValue122": 143,
    "DataCardValue123": 148,
    "DataCardValue124": 153,
    "DataCardValue125": 158,
    "DataCardValue126": 163,
    "DataCardValue127": 168,
    "DataCardValue128": 173,
    "DataCardValue129": 178,
    "DataCardValue13": 290,
    "DataCardValue130": 183,
    "DataCardValue131": 188,
    "DataCardValue132": 193,
    "DataCardValue133": 198,
    "DataCardValue134": 203,
    "DataCardValue135": 208,
    "DataCardValue136": 213,
    "DataCardValue139": 218,
    "DataCardValue14": 312,
    "DataCardValue15": 295,
    "DataCardValue16": 300,
    "DataCardValue17": 305,
    "DataCardValue18": 492,
    "DataCardValue19": 617,
    "DataCardValue2": 235,
    "DataCardValue20": 55,
    "DataCardValue21": 60,
    "DataCardValue22": 65,
    "DataCardValue23": 70,
    "DataCardValue24": 75,
    "DataCardValue25": 80,
    "DataCardValue26": 85,
    "DataCardValue27": 90,
    "DataCardValue28": 719,
    "DataCardValue29": 724,
    "DataCardValue3": 240,
    "DataCardValue30": 327,
    "DataCardValue31": 337,
    "DataCardValue32": 332,
    "DataCardValue33": 729,
    "DataCardValue34": 734,
    "DataCardValue35": 739,
    "DataCardValue36": 744,
    "DataCardValue37": 749,
    "DataCardValue38": 754,
    "DataCardValue39": 759,
    "DataCardValue4": 260,
    "DataCardValue40": 764,
    "DataCardValue41": 769,
    "DataCardValue42": 774,
    "DataCardValue43": 779,
    "DataCardValue44": 784,
    "DataCardValue45": 789,
    "DataCardValue46": 794,
    "DataCardValue47": 799,
    "DataCardValue48": 804,
    "DataCardValue5": 245,
    "DataCardValue50": 612,
    "DataCardValue50_1": 487,
    "DataCardValue52": 622,
    "DataCardValue52_1": 497,
    "DataCardValue53": 627,
    "DataCardValue53_1": 502,
    "DataCardValue54": 632,
    "DataCardValue54_1": 507,
    "DataCardValue55": 637,
    "DataCardValue55_1": 512,
    "DataCardValue56": 642,
    "DataCardValue56_1": 517,
    "DataCardValue57": 647,
    "DataCardValue57_1": 522,
    "DataCardValue58": 652,
    "DataCardValue58_1": 529,
    "DataCardValue59": 657,
    "DataCardValue59_1": 532,
    "DataCardValue6": 250,
    "DataCardValue60": 662,
    "DataCardValue60_1": 539,
    "DataCardValue61": 667,
    "DataCardValue61_1": 542,
    "DataCardValue62": 672,
    "DataCardValue62_1": 547,
    "DataCardValue63": 677,
    "DataCardValue63_1": 552,
    "DataCardValue67": 366,
    "DataCardValue67_1": 404,
    "DataCardValue7": 255,
    "DataCardValue71": 381,
    "DataCardValue71_1": 419,
    "DataCardValue72": 376,
    "DataCardValue72_1": 414,
    "DataCardValue73": 386,
    "DataCardValue73_1": 424,
    "DataCardValue74": 371,
    "DataCardValue74_1": 409,
    "DataCardValue75": 391,
    "DataCardValue75_1": 429,
    "DataCardValue8": 265,
    "DataCardValue9": 270,
    "DataCardValue90": 353,
    "DataCardValue93": 561,
    "DataCardValue93_1": 436,
    "DataCardValue94": 566,
    "DataCardValue94_1": 441,
    "DataCardValue95": 581,
    "DataCardValue95_1": 456,
    "DataCardValue96": 571,
    "DataCardValue96_1": 446,
    "DataCardValue97": 586,
    "DataCardValue97_1": 461,
    "DataCardValue98": 576,
    "DataCardValue98_1": 451,
    "DataCardValue99": 591,
    "DataCardValue99_1": 466,
    "Datum bezoek_DataCard1": 363,
    "Datum bezoek_DataCard1_1": 401,
    "Datum_DataCard1": 324,
    "DatumVandaag_1": 226,
    "DatumVandaag_10": 687,
    "DatumVandaag_11": 32,
    "DatumVandaag_12": 701,
    "DatumVandaag_2": 106,
    "DatumVandaag_3": 48,
    "DatumVandaag_4": 707,
    "DatumVandaag_5": 7,
    "DatumVandaag_6": 361,
    "DatumVandaag_7": 320,
    "DatumVandaag_8": 346,
    "DatumVandaag_9": 399,
    "DinsdagOpen_DataCard1": 621,
    "DinsdagOpen_DataCard1_1": 496,
    "DinsdagSluiting_DataCard1": 626,
    "DinsdagSluiting_DataCard1_1": 501,
    "DocumentenDossier": 342,
    "DonderdagOpen_DataCard1": 641,
    "DonderdagOpen_DataCard1_1": 516,
    "DonderdagSluiting_DataCard1": 646,
    "DonderdagSluiting_DataCard1_1": 521,
    "Elektriciteit_DataCard2": 155,
    "Email_DataCard1": 82,
    "ErrorMessage1": 233,
    "ErrorMessage10": 278,
    "ErrorMessage108": 114,
    "ErrorMessage109": 119,
    "ErrorMessage11": 283,
    "ErrorMessage110": 124,
    "ErrorMessage111": 129,
    "ErrorMessage112": 134,
    "ErrorMessage113": 139,
    "ErrorMessage114": 144,
    "ErrorMessage115": 149,
    "ErrorMessage116": 154,
    "ErrorMessage117": 159,
    "ErrorMessage118": 164,
    "ErrorMessage119": 169,
    "ErrorMessage12": 288,
    "ErrorMessage120": 174,
    "ErrorMessage121": 179,
    "ErrorMessage122": 184,
    "ErrorMessage123": 189,
    "ErrorMessage124": 194,
    "ErrorMessage125": 199,
    "ErrorMessage126": 204,
    "ErrorMessage127": 209,
    "ErrorMessage128": 214,
    "ErrorMessage129": 219,
    "ErrorMessage13": 293,
    "ErrorMessage14": 313,
    "ErrorMessage15": 298,
    "ErrorMessage16": 303,
    "ErrorMessage17": 308,
    "ErrorMessage18": 495,
    "ErrorMessage19": 56,
    "ErrorMessage2": 238,
    "ErrorMessage20": 61,
    "ErrorMessage21": 66,
    "ErrorMessage22": 71,
    "ErrorMessage23": 76,
    "ErrorMessage24": 81,
    "ErrorMessage25": 86,
    "ErrorMessage26": 91,
    "ErrorMessage27": 720,
    "ErrorMessage28": 725,
    "ErrorMessage29": 328,
    "ErrorMessage3": 243,
    "ErrorMessage30": 338,
    "ErrorMessage31": 333,
    "ErrorMessage32": 730,
    "ErrorMessage33": 735,
    "ErrorMessage34": 740,
    "ErrorMessage35": 745,
    "ErrorMessage36": 750,
    "ErrorMessage37": 755,
    "ErrorMessage38": 760,
    "ErrorMessage39": 765,
    "ErrorMessage4": 263,
    "ErrorMessage40": 770,
    "ErrorMessage41": 620,
    "ErrorMessage42": 775,
    "ErrorMessage43": 780,
    "ErrorMessage44": 785,
    "ErrorMessage45": 790,
    "ErrorMessage46": 795,
    "ErrorMessage47": 800,
    "ErrorMessage5": 248,
    "ErrorMessage50": 615,
    "ErrorMessage50_1": 490,
    "ErrorMessage52": 625,
    "ErrorMessage52_1": 500,
    "ErrorMessage53": 630,
    "ErrorMessage53_1": 505,
    "ErrorMessage54": 635,
    "ErrorMessage54_1": 510,
    "ErrorMessage55": 640,
    "ErrorMessage55_1": 515,
    "ErrorMessage56": 645,
    "ErrorMessage56_1": 520,
    "ErrorMessage57": 650,
    "ErrorMessage57_1": 525,
    "ErrorMessage58": 655,
    "ErrorMessage58_1": 530,
    "ErrorMessage59": 660,
    "ErrorMessage59_1": 535,
    "ErrorMessage6": 253,
    "ErrorMessage60": 665,
    "ErrorMessage60_1": 540,
    "ErrorMessage61": 670,
    "ErrorMessage61_1": 545,
    "ErrorMessage62": 675,
    "ErrorMessage62_1": 550,
    "ErrorMessage63": 680,
    "ErrorMessage63_1": 555,
    "ErrorMessage64": 367,
    "ErrorMessage64_1": 405,
    "ErrorMessage68": 382,
    "ErrorMessage68_1": 420,
    "ErrorMessage69": 377,
    "ErrorMessage69_1": 415,
    "ErrorMessage7": 258,
    "ErrorMessage70": 387,
    "ErrorMessage70_1": 425,
    "ErrorMessage71": 372,
    "ErrorMessage71_1": 410,
    "ErrorMessage72": 392,
    "ErrorMessage72_1": 430,
    "ErrorMessage8": 268,
    "ErrorMessage86": 354,
    "ErrorMessage89": 564,
    "ErrorMessage89_1": 439,
    "ErrorMessage9": 273,
    "ErrorMessage90": 569,
    "ErrorMessage90_1": 444,
    "ErrorMessage91": 584,
    "ErrorMessage91_1": 459,
    "ErrorMessage92": 574,
    "ErrorMessage92_1": 449,
    "ErrorMessage93": 589,
    "ErrorMessage93_1": 464,
    "ErrorMessage94": 579,
    "ErrorMessage94_1": 454,
    "ErrorMessage95": 594,
    "ErrorMessage95_1": 469,
    "ErrorMessage96": 599,
    "ErrorMessage96_1": 474,
    "ErrorMessage97": 604,
    "ErrorMessage97_1": 479,
    "ErrorMessage98": 609,
    "ErrorMessage98_1": 484,
    "EWG/MAAND_DataCard2": 145,
    "Familienaam contact_DataCard1": 62,
    "Financien": 102,
    "Form1": 716,
    "Form2": 42,
    "Form4": 349,
    "FormContact": 51,
    "FormFinanciën": 109,
    "FormOpeningsUren": 610,
    "FormOpeningsUren_1": 485,
    "FormPersoonGegevens": 228,
    "FormToevoegenVerslag": 362,
    "FormToevoegenWinkel": 559,
    "FormToevoegenWinkel_1": 434,
    "FormWijzigenVerslag": 400,
    "Gallery1": 708,
    "Gallery3": 8,
    "Gallery4": 92,
    "Gallery5": 19,
    "Gallery6": 691,
    "galleryTemplate1": 709,
    "galleryTemplate3": 9,
    "galleryTemplate4": 93,
    "galleryTemplate5": 692,
    "galleryTemplate6": 20,
    "Gas_DataCard2": 150,
    "Gast_DataCard1": 87,
    "Gast_DataCard2": 329,
    "Gast_DataCard4": 215,
    "Geboortedatum_DataCard1": 259,
    "Geboortedatum_DataCard2": 732,
    "Gelinkte dossiers_DataCard1": 304,
    "Gelinkte dossiers_DataCard2": 797,
    "Gemeente_DataCard1": 254,
    "Gemeente_DataCard2": 72,
    "Gemeente_DataCard3": 747,
    "Gemeente_DataCard5": 575,
    "Gemeente_DataCard5_1": 450,
    "Geslacht_DataCard1": 289,
    "Geslacht_DataCard2": 777,
    "Hoofdmenu": 31,
    "Hoofdmenu_1": 225,
    "Hoofdmenu_10": 686,
    "Hoofdmenu_11": 700,
    "Hoofdmenu_2": 105,
    "Hoofdmenu_3": 47,
    "Hoofdmenu_4": 706,
    "Hoofdmenu_5": 6,
    "Hoofdmenu_6": 360,
    "Hoofdmenu_7": 319,
    "Hoofdmenu_8": 345,
    "Hoofdmenu_9": 398,
    "Huur_DataCard2": 140,
    "Icon1": 99,
    "Icon3": 689,
    "Image4": 30,
    "Image4_1": 224,
    "Image4_10": 685,
    "Image4_11": 699,
    "Image4_2": 104,
    "Image4_3": 46,
    "Image4_4": 705,
    "Image4_5": 5,
    "Image4_6": 359,
    "Image4_7": 318,
    "Image4_8": 344,
    "Image4_9": 397,
    "Kennis Nederlands_DataCard1": 284,
    "Kennis Nederlands_DataCard2": 772,
    "Kierbezoeken": 703,
    "Kindergeld_DataCard2": 130,
    "Label1": 108,
    "Label1_1": 50,
    "Label1_2": 322,
    "Label1_3": 348,
    "Label2_1": 227,
    "Label2_2": 33,
    "Label2_3": 107,
    "Label2_4": 49,
    "Label2_5": 321,
    "Label2_6": 347,
    "Label2_7": 688,
    "Label2_8": 702,
    "Leefloon OCMW_DataCard2": 120,
    "LijstStuurgroep": 38,
    "Loon_DataCard2": 110,
    "MaandagOpen_DataCard1": 611,
    "MaandagOpen_DataCard1_1": 486,
    "MaandagSluiting_DataCard1": 616,
    "MaandagSluiting_DataCard2": 491,
    "Manier van aanmelden_DataCard1": 383,
    "Manier van aanmelden_DataCard1_1": 421,
    "Medische kosten_DataCard2": 185,
    "Moedertaal_DataCard1": 269,
    "Moedertaal_DataCard2": 757,
    "Mutualiteit_DataCard2": 180,
    "Naam bezoeker_DataCard1": 368,
    "Naam bezoeker_DataCard1_1": 406,
    "Naam_DataCard1": 229,
    "Naam_DataCard2": 717,
    "Nationaliteit_DataCard1": 264,
    "Nationaliteit_DataCard2": 752,
    "NextArrow3": 711,
    "NextArrow4": 23,
    "NextArrow5": 11,
    "NextArrow6": 95,
    "NextArrow8": 694,
    "NieuwBezoeksverlag": 37,
    "NieuwIntake": 34,
    "Nodige Informatie_DataCard4": 595,
    "Nodige Informatie_DataCard4_1": 470,
    "Omniostatuut_DataCard1": 279,
    "Omniostatuut_DataCard2": 767,
    "Opmerking_DataCard1": 334,
    "Opmerkingen_DataCard4": 600,
    "Opmerkingen_DataCard4_1": 475,
    "OpmerkingenDossier": 316,
    "OpmerkingsForm": 323,
    "OverzichtBezoekverslagen": 3,
    "OverzichtGasten": 683,
    "OverzichtPersoonGegevens": 697,
    "OverzichtWinkels": 16,
    "Permanentienaam_DataCard1": 378,
    "Permanentienaam_DataCard1_1": 416,
    "PersoonGegevens": 222,
    "Postcode_DataCard1": 249,
    "Postcode_DataCard2": 77,
    "Postcode_DataCard3": 742,
    "Postcode_DataCard5": 570,
    "Postcode_DataCard5_1": 445,
    "Rectangle1": 29,
    "Rectangle1_1": 223,
    "Rectangle1_10": 684,
    "Rectangle1_11": 698,
    "Rectangle1_2": 103,
    "Rectangle1_3": 45,
    "Rectangle1_4": 704,
    "Rectangle1_5": 4,
    "Rectangle1_6": 358,
    "Rectangle1_7": 317,
    "Rectangle1_8": 343,
    "Rectangle1_9": 396,
    "RectQuickActionBar1": 17,
    "Rijksregisternummer_DataCard1": 299,
    "Rijksregisternummer_DataCard2": 792,
    "Schoolgeld_DataCard2": 165,
    "Separator3": 713,
    "Separator4": 25,
    "Separator5": 13,
    "Separator6": 97,
    "Separator8": 696,
    "Soort contact_DataCard1": 52,
    "Soort gast_DataCard1": 239,
    "Soort gast_DataCard2": 727,
    "Startscherm": 28,
    "StarVisible1": 231,
    "StarVisible10": 276,
    "StarVisible108": 111,
    "StarVisible109": 116,
    "StarVisible11": 281,
    "StarVisible110": 121,
    "StarVisible111": 126,
    "StarVisible112": 131,
    "StarVisible113": 136,
    "StarVisible114": 141,
    "StarVisible115": 146,
    "StarVisible116": 151,
    "StarVisible117": 156,
    "StarVisible118": 161,
    "StarVisible119": 166,
    "StarVisible12": 286,
    "StarVisible120": 171,
    "StarVisible121": 176,
    "StarVisible122": 181,
    "StarVisible123": 186,
    "StarVisible124": 191,
    "StarVisible125": 196,
    "StarVisible126": 201,
    "StarVisible127": 206,
    "StarVisible128": 211,
    "StarVisible129": 216,
    "StarVisible13": 291,
    "StarVisible14": 310,
    "StarVisible15": 296,
    "StarVisible16": 301,
    "StarVisible17": 306,
    "StarVisible18": 493,
    "StarVisible19": 53,
    "StarVisible2": 236,
    "StarVisible20": 58,
    "StarVisible21": 63,
    "StarVisible22": 68,
    "StarVisible23": 73,
    "StarVisible24": 78,
    "StarVisible25": 83,
    "StarVisible26": 88,
    "StarVisible27": 721,
    "StarVisible28": 726,
    "StarVisible29": 325,
    "StarVisible3": 241,
    "StarVisible30": 335,
    "StarVisible31": 330,
    "StarVisible32": 731,
    "StarVisible33": 736,
    "StarVisible34": 741,
    "StarVisible35": 746,
    "StarVisible36": 751,
    "StarVisible37": 756,
    "StarVisible38": 761,
    "StarVisible39": 766,
    "StarVisible4": 261,
    "StarVisible40": 771,
    "StarVisible41": 618,
    "StarVisible42": 776,
    "StarVisible43": 781,
    "StarVisible44": 786,
    "StarVisible45": 791,
    "StarVisible46": 796,
    "StarVisible47": 801,
    "StarVisible5": 246,
    "StarVisible50": 614,
    "StarVisible50_1": 489,
    "StarVisible52": 623,
    "StarVisible52_1": 499,
    "StarVisible53": 628,
    "StarVisible53_1": 503,
    "StarVisible54": 633,
    "StarVisible54_1": 509,
    "StarVisible55": 638,
    "StarVisible55_1": 513,
    "StarVisible56": 643,
    "StarVisible56_1": 519,
    "StarVisible57": 648,
    "StarVisible57_1": 523,
    "StarVisible58": 653,
    "StarVisible58_1": 528,
    "StarVisible59": 658,
    "StarVisible59_1": 533,
    "StarVisible6": 251,
    "StarVisible60": 663,
    "StarVisible60_1": 538,
    "StarVisible61": 668,
    "StarVisible61_1": 543,
    "StarVisible62": 673,
    "StarVisible62_1": 549,
    "StarVisible63": 678,
    "StarVisible63_1": 553,
    "StarVisible64": 364,
    "StarVisible64_1": 402,
    "StarVisible68": 379,
    "StarVisible68_1": 417,
    "StarVisible69": 374,
    "StarVisible69_1": 412,
    "StarVisible7": 256,
    "StarVisible70": 384,
    "StarVisible70_1": 422,
    "StarVisible71": 369,
    "StarVisible71_1": 407,
    "StarVisible72": 389,
    "StarVisible72_1": 427,
    "StarVisible8": 266,
    "StarVisible86": 351,
    "StarVisible89": 562,
    "StarVisible89_1": 437,
    "StarVisible9": 271,
    "StarVisible90": 567,
    "StarVisible90_1": 442,
    "StarVisible91": 582,
    "StarVisible91_1": 457,
    "StarVisible92": 572,
    "StarVisible92_1": 447,
    "StarVisible93": 587,
    "StarVisible93_1": 462,
    "StarVisible94": 577,
    "StarVisible94_1": 452,
    "StarVisible95": 592,
    "StarVisible95_1": 467,
    "StarVisible96": 597,
    "StarVisible96_1": 472,
    "StarVisible97": 602,
    "StarVisible97_1": 477,
    "StarVisible98": 607,
    "StarVisible98_1": 482,
    "Stempelgeld_DataCard2": 115,
    "Subtitle3": 712,
    "Subtitle4": 22,
    "Subtitle5": 12,
    "Subtitle6": 96,
    "Subtitle8": 695,
    "Telefoon/Internet/TV_DataCard2": 170,
    "Telefoon_DataCard4": 580,
    "Telefoon_DataCard4_1": 455,
    "Telefoonnummer_DataCard1": 67,
    "TextInput1": 690,
    "Title_DataCard4": 560,
    "Title_DataCard4_1": 435,
    "Title1": 18,
    "Title4": 710,
    "Title5": 21,
    "Title6": 10,
    "Title7": 94,
    "Title9": 693,
    "ToevoegenBezoekverslag": 357,
    "ToevoegenKierbezoek": 41,
    "ToevoegenWinkel": 558,
    "Verantwoordelijke winkel_DataCard4": 585,
    "Verantwoordelijke winkel_DataCard4_1": 460,
    "Verslag_DataCard1": 388,
    "Verslag_DataCard1_1": 426,
    "Vervoerskosten_DataCard2": 175,
    "Verzekeringen_DataCard2": 190,
    "Volgende": 315,
    "Volledige Naam_DataCard1": 802,
    "Voor stuurgroep_DataCard1": 373,
    "Voor stuurgroep_DataCard1_1": 411,
    "Voornaam contact_DataCard1": 57,
    "Voornaam_DataCard1": 234,
    "Voornaam_DataCard2": 722,
    "VrijdagOpen_DataCard1": 651,
    "VrijdagOpen_DataCard1_1": 526,
    "VrijdagSluiting_DataCard1": 656,
    "VrijdagSluiting_DataCard1_1": 531,
    "Water_DataCard2": 160,
    "WijzigenBezoeksverslag": 395,
    "WijzigenWinkel": 433,
    "Winkelregel_DataCard4": 590,
    "Winkelregel_DataCard4_1": 465,
    "WinkelToevoegen": 27,
    "WinkelToevoegen_1": 15,
    "WoensdagOpen_DataCard1": 631,
    "WoensdagOpen_DataCard1_1": 506,
    "WoensdagSluiting_DataCard1": 636,
    "WoensdagSluiting_DataCard1_1": 511,
    "ZaterdagOpen_DataCard1": 661,
    "ZaterdagOpen_DataCard1_1": 536,
    "ZaterdagSluiting_DataCard1": 666,
    "ZaterdagSluiting_DataCard1_1": 541,
    "Ziekteuitkering_DataCard2": 125,
    "ZondagOpen_DataCard1": 671,
    "ZondagOpen_DataCard1_1": 546,
    "ZondagSluiting_DataCard1": 676,
    "ZondagSluiting_DataCard1_1": 551
  },
  "FunctionParamsInvariantScripts": {},
  "FunctionParamsInvariantScriptsOnInstances": {},
  "HeaderLastSavedDateTimeUTC": "02/16/2023 15:53:42",
  "IsLegacyComponentAllowGlobalScopeCase": false,
  "LocalConnectionIDReferences": {
    "21ef9927-9708-4ba0-b8aa-9e50e12eda06": "\"/providers/microsoft.powerapps/apis/shared_sharepointonline/connections/e1922b9fa4114495b0586d3d570cf46a\""
  },
  "LocalDatabaseReferencesAsEmpty": false,
  "LocalResourceFileNames": {
    "MicrosoftTeams-image": "0002.png",
    "MicrosoftTeams-image (1)": "0001.png"
  },
  "LocalResourceRootPaths": {
    "MicrosoftTeams-image": "https://docserverpwaprodneu.blob.core.windows.net/8b95c11a-5344-48cb-b03f-f93171c2ac1c-1/resource/Assets0Images00002.png?sv=2018-03-28&sr=b&sig=%2FzoIULHZcX%2BbwbD5XrW1%2FSU30tNSMsl2brU%2FSZtb%2F0w%3D&spr=https&se=2023-02-17T15%3A44%3A53Z&sp=r",
    "MicrosoftTeams-image (1)": "https://docserverpwaprodneu.blob.core.windows.net/8b95c11a-5344-48cb-b03f-f93171c2ac1c-1/resource/Assets0Images00001.png?sv=2018-03-28&sr=b&sig=E9WRGBfnpRXEx8inp0ub7f829jtfX8NjsCZAevmjGCY%3D&spr=https&se=2023-02-17T15%3A44%3A53Z&sp=r"
  },
  "OrderComponentMetadata": {},
  "OrderComponentTemplate": {},
  "OrderDataSource": {
    "Bezoekverslagen": 6,
    "ComboBoxSample": 0,
    "Contacten_1": 1,
    "CustomGallerySample": 2,
    "Documents": 3,
    "Financiën": 4,
    "Gasten": 5,
    "ListboxSample": 7,
    "Opmerkingen": 8,
    "Winkels_1": 9
  },
  "OrderGroupControls": {},
  "OrderPcfTemplate": {},
  "OrderTemplate": {},
  "OrderXMLTemplate": {
    "attachments": 11,
    "button": 5,
    "combobox": 7,
    "datepicker": 9,
    "form": 6,
    "gallery": 3,
    "icon": 4,
    "image": 1,
    "label": 2,
    "rectangle": 0,
    "text": 8,
    "toggleSwitch": 10
  },
  "OverridablePropertiesEntry": {
    "Actief_DataCard1": {},
    "Actief_DataCard2": {},
    "Adres_DataCard1": {},
    "Adres_DataCard2": {},
    "Adres_DataCard5": {},
    "Adres_DataCard5_1": {},
    "Afbetalingen_DataCard2": {},
    "Afspraken_DataCard4": {},
    "Afspraken_DataCard4_1": {},
    "Alimentatieuit_DataCard2": {},
    "Andere inkomsten_DataCard2": {},
    "Andere uitgaven_DataCard2": {},
    "App": {},
    "Attachments_DataCard3": {},
    "Bezoeker_DataCard2": {},
    "Body1": {},
    "Budgetmeter_DataCard2": {},
    "Burgerlijke staat_DataCard1": {},
    "Burgerlijke staat_DataCard2": {},
    "Button1": {},
    "Button1_1": {},
    "Button1_2": {},
    "Button1_3": {},
    "Button10": {},
    "Button11": {},
    "Button12": {},
    "Button13": {},
    "Button13_1": {},
    "Button14": {},
    "Button14_1": {},
    "Button14_2": {},
    "Button14_3": {},
    "Button15": {},
    "Button15_1": {},
    "Button15_4": {},
    "Button15_5": {},
    "Button2": {},
    "Button2_1": {},
    "Button2_2": {},
    "Button2_3": {},
    "Button3": {},
    "Button4": {},
    "Button5": {},
    "Button6": {},
    "Button6_1": {},
    "Button7": {},
    "Button7_1": {},
    "Button8": {},
    "Button8_1": {},
    "Button9": {},
    "ContactenScherm": {},
    "Dakloos_DataCard1": {},
    "Dakloos_DataCard2": {},
    "DataCardKey1": {},
    "DataCardKey10": {},
    "DataCardKey100": {},
    "DataCardKey100_1": {},
    "DataCardKey101": {},
    "DataCardKey101_1": {},
    "DataCardKey102": {},
    "DataCardKey102_1": {},
    "DataCardKey11": {},
    "DataCardKey115": {},
    "DataCardKey116": {},
    "DataCardKey117": {},
    "DataCardKey118": {},
    "DataCardKey119": {},
    "DataCardKey12": {},
    "DataCardKey120": {},
    "DataCardKey122": {},
    "DataCardKey123": {},
    "DataCardKey124": {},
    "DataCardKey125": {},
    "DataCardKey126": {},
    "DataCardKey127": {},
    "DataCardKey128": {},
    "DataCardKey129": {},
    "DataCardKey13": {},
    "DataCardKey130": {},
    "DataCardKey131": {},
    "DataCardKey132": {},
    "DataCardKey133": {},
    "DataCardKey134": {},
    "DataCardKey135": {},
    "DataCardKey136": {},
    "DataCardKey139": {},
    "DataCardKey14": {},
    "DataCardKey15": {},
    "DataCardKey16": {},
    "DataCardKey17": {},
    "DataCardKey18": {},
    "DataCardKey19": {},
    "DataCardKey2": {},
    "DataCardKey20": {},
    "DataCardKey21": {},
    "DataCardKey22": {},
    "DataCardKey23": {},
    "DataCardKey24": {},
    "DataCardKey25": {},
    "DataCardKey26": {},
    "DataCardKey27": {},
    "DataCardKey28": {},
    "DataCardKey29": {},
    "DataCardKey3": {},
    "DataCardKey30": {},
    "DataCardKey31": {},
    "DataCardKey32": {},
    "DataCardKey33": {},
    "DataCardKey34": {},
    "DataCardKey35": {},
    "DataCardKey36": {},
    "DataCardKey37": {},
    "DataCardKey38": {},
    "DataCardKey39": {},
    "DataCardKey4": {},
    "DataCardKey40": {},
    "DataCardKey41": {},
    "DataCardKey42": {},
    "DataCardKey43": {},
    "DataCardKey44": {},
    "DataCardKey45": {},
    "DataCardKey46": {},
    "DataCardKey47": {},
    "DataCardKey48": {},
    "DataCardKey5": {},
    "DataCardKey50": {},
    "DataCardKey50_1": {},
    "DataCardKey52": {},
    "DataCardKey52_1": {},
    "DataCardKey53": {},
    "DataCardKey53_1": {},
    "DataCardKey54": {},
    "DataCardKey54_1": {},
    "DataCardKey55": {},
    "DataCardKey55_1": {},
    "DataCardKey56": {},
    "DataCardKey56_1": {},
    "DataCardKey57": {},
    "DataCardKey57_1": {},
    "DataCardKey58": {},
    "DataCardKey58_1": {},
    "DataCardKey59": {},
    "DataCardKey59_1": {},
    "DataCardKey6": {},
    "DataCardKey60": {},
    "DataCardKey60_1": {},
    "DataCardKey61": {},
    "DataCardKey61_1": {},
    "DataCardKey62": {},
    "DataCardKey62_1": {},
    "DataCardKey63": {},
    "DataCardKey63_1": {},
    "DataCardKey67": {},
    "DataCardKey67_1": {},
    "DataCardKey7": {},
    "DataCardKey71": {},
    "DataCardKey71_1": {},
    "DataCardKey72": {},
    "DataCardKey72_1": {},
    "DataCardKey73": {},
    "DataCardKey73_1": {},
    "DataCardKey74": {},
    "DataCardKey74_1": {},
    "DataCardKey75": {},
    "DataCardKey75_1": {},
    "DataCardKey8": {},
    "DataCardKey9": {},
    "DataCardKey90": {},
    "DataCardKey93": {},
    "DataCardKey93_1": {},
    "DataCardKey94": {},
    "DataCardKey94_1": {},
    "DataCardKey95": {},
    "DataCardKey95_1": {},
    "DataCardKey96": {},
    "DataCardKey96_1": {},
    "DataCardKey97": {},
    "DataCardKey97_1": {},
    "DataCardKey98": {},
    "DataCardKey98_1": {},
    "DataCardKey99": {},
    "DataCardKey99_1": {},
    "DataCardValue1": {},
    "DataCardValue10": {},
    "DataCardValue100": {},
    "DataCardValue100_1": {},
    "DataCardValue101": {},
    "DataCardValue101_1": {},
    "DataCardValue102": {},
    "DataCardValue102_1": {},
    "DataCardValue11": {},
    "DataCardValue115": {},
    "DataCardValue116": {},
    "DataCardValue117": {},
    "DataCardValue118": {},
    "DataCardValue119": {},
    "DataCardValue12": {},
    "DataCardValue120": {},
    "DataCardValue122": {},
    "DataCardValue123": {},
    "DataCardValue124": {},
    "DataCardValue125": {},
    "DataCardValue126": {},
    "DataCardValue127": {},
    "DataCardValue128": {},
    "DataCardValue129": {},
    "DataCardValue13": {},
    "DataCardValue130": {},
    "DataCardValue131": {},
    "DataCardValue132": {},
    "DataCardValue133": {},
    "DataCardValue134": {},
    "DataCardValue135": {},
    "DataCardValue136": {},
    "DataCardValue139": {},
    "DataCardValue14": {},
    "DataCardValue15": {},
    "DataCardValue16": {},
    "DataCardValue17": {},
    "DataCardValue18": {},
    "DataCardValue19": {},
    "DataCardValue2": {},
    "DataCardValue20": {},
    "DataCardValue21": {},
    "DataCardValue22": {},
    "DataCardValue23": {},
    "DataCardValue24": {},
    "DataCardValue25": {},
    "DataCardValue26": {},
    "DataCardValue27": {},
    "DataCardValue28": {},
    "DataCardValue29": {},
    "DataCardValue3": {},
    "DataCardValue30": {},
    "DataCardValue31": {},
    "DataCardValue32": {},
    "DataCardValue33": {},
    "DataCardValue34": {},
    "DataCardValue35": {},
    "DataCardValue36": {},
    "DataCardValue37": {},
    "DataCardValue38": {},
    "DataCardValue39": {},
    "DataCardValue4": {},
    "DataCardValue40": {},
    "DataCardValue41": {},
    "DataCardValue42": {},
    "DataCardValue43": {},
    "DataCardValue44": {},
    "DataCardValue45": {},
    "DataCardValue46": {},
    "DataCardValue47": {},
    "DataCardValue48": {},
    "DataCardValue5": {},
    "DataCardValue50": {},
    "DataCardValue50_1": {},
    "DataCardValue52": {},
    "DataCardValue52_1": {},
    "DataCardValue53": {},
    "DataCardValue53_1": {},
    "DataCardValue54": {},
    "DataCardValue54_1": {},
    "DataCardValue55": {},
    "DataCardValue55_1": {},
    "DataCardValue56": {},
    "DataCardValue56_1": {},
    "DataCardValue57": {},
    "DataCardValue57_1": {},
    "DataCardValue58": {},
    "DataCardValue58_1": {},
    "DataCardValue59": {},
    "DataCardValue59_1": {},
    "DataCardValue6": {},
    "DataCardValue60": {},
    "DataCardValue60_1": {},
    "DataCardValue61": {},
    "DataCardValue61_1": {},
    "DataCardValue62": {},
    "DataCardValue62_1": {},
    "DataCardValue63": {},
    "DataCardValue63_1": {},
    "DataCardValue67": {},
    "DataCardValue67_1": {},
    "DataCardValue7": {},
    "DataCardValue71": {},
    "DataCardValue71_1": {},
    "DataCardValue72": {},
    "DataCardValue72_1": {},
    "DataCardValue73": {},
    "DataCardValue73_1": {},
    "DataCardValue74": {},
    "DataCardValue74_1": {},
    "DataCardValue75": {},
    "DataCardValue75_1": {},
    "DataCardValue8": {},
    "DataCardValue9": {},
    "DataCardValue90": {},
    "DataCardValue93": {},
    "DataCardValue93_1": {},
    "DataCardValue94": {},
    "DataCardValue94_1": {},
    "DataCardValue95": {},
    "DataCardValue95_1": {},
    "DataCardValue96": {},
    "DataCardValue96_1": {},
    "DataCardValue97": {},
    "DataCardValue97_1": {},
    "DataCardValue98": {},
    "DataCardValue98_1": {},
    "DataCardValue99": {},
    "DataCardValue99_1": {},
    "Datum bezoek_DataCard1": {},
    "Datum bezoek_DataCard1_1": {},
    "Datum_DataCard1": {},
    "DatumVandaag_1": {},
    "DatumVandaag_10": {},
    "DatumVandaag_11": {},
    "DatumVandaag_12": {},
    "DatumVandaag_2": {},
    "DatumVandaag_3": {},
    "DatumVandaag_4": {},
    "DatumVandaag_5": {},
    "DatumVandaag_6": {},
    "DatumVandaag_7": {},
    "DatumVandaag_8": {},
    "DatumVandaag_9": {},
    "DinsdagOpen_DataCard1": {},
    "DinsdagOpen_DataCard1_1": {},
    "DinsdagSluiting_DataCard1": {},
    "DinsdagSluiting_DataCard1_1": {},
    "DocumentenDossier": {},
    "DonderdagOpen_DataCard1": {},
    "DonderdagOpen_DataCard1_1": {},
    "DonderdagSluiting_DataCard1": {},
    "DonderdagSluiting_DataCard1_1": {},
    "Elektriciteit_DataCard2": {},
    "Email_DataCard1": {},
    "ErrorMessage1": {},
    "ErrorMessage10": {},
    "ErrorMessage108": {},
    "ErrorMessage109": {},
    "ErrorMessage11": {},
    "ErrorMessage110": {},
    "ErrorMessage111": {},
    "ErrorMessage112": {},
    "ErrorMessage113": {},
    "ErrorMessage114": {},
    "ErrorMessage115": {},
    "ErrorMessage116": {},
    "ErrorMessage117": {},
    "ErrorMessage118": {},
    "ErrorMessage119": {},
    "ErrorMessage12": {},
    "ErrorMessage120": {},
    "ErrorMessage121": {},
    "ErrorMessage122": {},
    "ErrorMessage123": {},
    "ErrorMessage124": {},
    "ErrorMessage125": {},
    "ErrorMessage126": {},
    "ErrorMessage127": {},
    "ErrorMessage128": {},
    "ErrorMessage129": {},
    "ErrorMessage13": {},
    "ErrorMessage14": {},
    "ErrorMessage15": {},
    "ErrorMessage16": {},
    "ErrorMessage17": {},
    "ErrorMessage18": {},
    "ErrorMessage19": {},
    "ErrorMessage2": {},
    "ErrorMessage20": {},
    "ErrorMessage21": {},
    "ErrorMessage22": {},
    "ErrorMessage23": {},
    "ErrorMessage24": {},
    "ErrorMessage25": {},
    "ErrorMessage26": {},
    "ErrorMessage27": {},
    "ErrorMessage28": {},
    "ErrorMessage29": {},
    "ErrorMessage3": {},
    "ErrorMessage30": {},
    "ErrorMessage31": {},
    "ErrorMessage32": {},
    "ErrorMessage33": {},
    "ErrorMessage34": {},
    "ErrorMessage35": {},
    "ErrorMessage36": {},
    "ErrorMessage37": {},
    "ErrorMessage38": {},
    "ErrorMessage39": {},
    "ErrorMessage4": {},
    "ErrorMessage40": {},
    "ErrorMessage41": {},
    "ErrorMessage42": {},
    "ErrorMessage43": {},
    "ErrorMessage44": {},
    "ErrorMessage45": {},
    "ErrorMessage46": {},
    "ErrorMessage47": {},
    "ErrorMessage5": {},
    "ErrorMessage50": {},
    "ErrorMessage50_1": {},
    "ErrorMessage52": {},
    "ErrorMessage52_1": {},
    "ErrorMessage53": {},
    "ErrorMessage53_1": {},
    "ErrorMessage54": {},
    "ErrorMessage54_1": {},
    "ErrorMessage55": {},
    "ErrorMessage55_1": {},
    "ErrorMessage56": {},
    "ErrorMessage56_1": {},
    "ErrorMessage57": {},
    "ErrorMessage57_1": {},
    "ErrorMessage58": {},
    "ErrorMessage58_1": {},
    "ErrorMessage59": {},
    "ErrorMessage59_1": {},
    "ErrorMessage6": {},
    "ErrorMessage60": {},
    "ErrorMessage60_1": {},
    "ErrorMessage61": {},
    "ErrorMessage61_1": {},
    "ErrorMessage62": {},
    "ErrorMessage62_1": {},
    "ErrorMessage63": {},
    "ErrorMessage63_1": {},
    "ErrorMessage64": {},
    "ErrorMessage64_1": {},
    "ErrorMessage68": {},
    "ErrorMessage68_1": {},
    "ErrorMessage69": {},
    "ErrorMessage69_1": {},
    "ErrorMessage7": {},
    "ErrorMessage70": {},
    "ErrorMessage70_1": {},
    "ErrorMessage71": {},
    "ErrorMessage71_1": {},
    "ErrorMessage72": {},
    "ErrorMessage72_1": {},
    "ErrorMessage8": {},
    "ErrorMessage86": {},
    "ErrorMessage89": {},
    "ErrorMessage89_1": {},
    "ErrorMessage9": {},
    "ErrorMessage90": {},
    "ErrorMessage90_1": {},
    "ErrorMessage91": {},
    "ErrorMessage91_1": {},
    "ErrorMessage92": {},
    "ErrorMessage92_1": {},
    "ErrorMessage93": {},
    "ErrorMessage93_1": {},
    "ErrorMessage94": {},
    "ErrorMessage94_1": {},
    "ErrorMessage95": {},
    "ErrorMessage95_1": {},
    "ErrorMessage96": {},
    "ErrorMessage96_1": {},
    "ErrorMessage97": {},
    "ErrorMessage97_1": {},
    "ErrorMessage98": {},
    "ErrorMessage98_1": {},
    "EWG/MAAND_DataCard2": {},
    "Familienaam contact_DataCard1": {},
    "Financien": {},
    "Form1": {},
    "Form2": {},
    "Form4": {},
    "FormContact": {},
    "FormFinanciën": {},
    "FormOpeningsUren": {},
    "FormOpeningsUren_1": {},
    "FormPersoonGegevens": {},
    "FormToevoegenVerslag": {},
    "FormToevoegenWinkel": {},
    "FormToevoegenWinkel_1": {},
    "FormWijzigenVerslag": {},
    "Gallery1": {},
    "Gallery3": {},
    "Gallery4": {},
    "Gallery5": {},
    "Gallery6": {},
    "galleryTemplate1": {},
    "galleryTemplate3": {},
    "galleryTemplate4": {},
    "galleryTemplate5": {},
    "galleryTemplate6": {},
    "Gas_DataCard2": {},
    "Gast_DataCard1": {},
    "Gast_DataCard2": {},
    "Gast_DataCard4": {},
    "Geboortedatum_DataCard1": {},
    "Geboortedatum_DataCard2": {},
    "Gelinkte dossiers_DataCard1": {},
    "Gelinkte dossiers_DataCard2": {},
    "Gemeente_DataCard1": {},
    "Gemeente_DataCard2": {},
    "Gemeente_DataCard3": {},
    "Gemeente_DataCard5": {},
    "Gemeente_DataCard5_1": {},
    "Geslacht_DataCard1": {},
    "Geslacht_DataCard2": {},
    "Hoofdmenu": {},
    "Hoofdmenu_1": {},
    "Hoofdmenu_10": {},
    "Hoofdmenu_11": {},
    "Hoofdmenu_2": {},
    "Hoofdmenu_3": {},
    "Hoofdmenu_4": {},
    "Hoofdmenu_5": {},
    "Hoofdmenu_6": {},
    "Hoofdmenu_7": {},
    "Hoofdmenu_8": {},
    "Hoofdmenu_9": {},
    "Huur_DataCard2": {},
    "Icon1": {},
    "Icon3": {},
    "Image4": {},
    "Image4_1": {},
    "Image4_10": {},
    "Image4_11": {},
    "Image4_2": {},
    "Image4_3": {},
    "Image4_4": {},
    "Image4_5": {},
    "Image4_6": {},
    "Image4_7": {},
    "Image4_8": {},
    "Image4_9": {},
    "Kennis Nederlands_DataCard1": {},
    "Kennis Nederlands_DataCard2": {},
    "Kierbezoeken": {},
    "Kindergeld_DataCard2": {},
    "Label1": {},
    "Label1_1": {},
    "Label1_2": {},
    "Label1_3": {},
    "Label2_1": {},
    "Label2_2": {},
    "Label2_3": {},
    "Label2_4": {},
    "Label2_5": {},
    "Label2_6": {},
    "Label2_7": {},
    "Label2_8": {},
    "Leefloon OCMW_DataCard2": {},
    "LijstStuurgroep": {},
    "Loon_DataCard2": {},
    "MaandagOpen_DataCard1": {},
    "MaandagOpen_DataCard1_1": {},
    "MaandagSluiting_DataCard1": {},
    "MaandagSluiting_DataCard2": {},
    "Manier van aanmelden_DataCard1": {},
    "Manier van aanmelden_DataCard1_1": {},
    "Medische kosten_DataCard2": {},
    "Moedertaal_DataCard1": {},
    "Moedertaal_DataCard2": {},
    "Mutualiteit_DataCard2": {},
    "Naam bezoeker_DataCard1": {},
    "Naam bezoeker_DataCard1_1": {},
    "Naam_DataCard1": {},
    "Naam_DataCard2": {},
    "Nationaliteit_DataCard1": {},
    "Nationaliteit_DataCard2": {},
    "NextArrow3": {},
    "NextArrow4": {},
    "NextArrow5": {},
    "NextArrow6": {},
    "NextArrow8": {},
    "NieuwBezoeksverlag": {},
    "NieuwIntake": {},
    "Nodige Informatie_DataCard4": {},
    "Nodige Informatie_DataCard4_1": {},
    "Omniostatuut_DataCard1": {},
    "Omniostatuut_DataCard2": {},
    "Opmerking_DataCard1": {},
    "Opmerkingen_DataCard4": {},
    "Opmerkingen_DataCard4_1": {},
    "OpmerkingenDossier": {},
    "OpmerkingsForm": {},
    "OverzichtBezoekverslagen": {},
    "OverzichtGasten": {},
    "OverzichtPersoonGegevens": {},
    "OverzichtWinkels": {},
    "Permanentienaam_DataCard1": {},
    "Permanentienaam_DataCard1_1": {},
    "PersoonGegevens": {},
    "Postcode_DataCard1": {},
    "Postcode_DataCard2": {},
    "Postcode_DataCard3": {},
    "Postcode_DataCard5": {},
    "Postcode_DataCard5_1": {},
    "Rectangle1": {},
    "Rectangle1_1": {},
    "Rectangle1_10": {},
    "Rectangle1_11": {},
    "Rectangle1_2": {},
    "Rectangle1_3": {},
    "Rectangle1_4": {},
    "Rectangle1_5": {},
    "Rectangle1_6": {},
    "Rectangle1_7": {},
    "Rectangle1_8": {},
    "Rectangle1_9": {},
    "RectQuickActionBar1": {},
    "Rijksregisternummer_DataCard1": {},
    "Rijksregisternummer_DataCard2": {},
    "Schoolgeld_DataCard2": {},
    "Separator3": {},
    "Separator4": {},
    "Separator5": {},
    "Separator6": {},
    "Separator8": {},
    "Soort contact_DataCard1": {},
    "Soort gast_DataCard1": {},
    "Soort gast_DataCard2": {},
    "Startscherm": {},
    "StarVisible1": {},
    "StarVisible10": {},
    "StarVisible108": {},
    "StarVisible109": {},
    "StarVisible11": {},
    "StarVisible110": {},
    "StarVisible111": {},
    "StarVisible112": {},
    "StarVisible113": {},
    "StarVisible114": {},
    "StarVisible115": {},
    "StarVisible116": {},
    "StarVisible117": {},
    "StarVisible118": {},
    "StarVisible119": {},
    "StarVisible12": {},
    "StarVisible120": {},
    "StarVisible121": {},
    "StarVisible122": {},
    "StarVisible123": {},
    "StarVisible124": {},
    "StarVisible125": {},
    "StarVisible126": {},
    "StarVisible127": {},
    "StarVisible128": {},
    "StarVisible129": {},
    "StarVisible13": {},
    "StarVisible14": {},
    "StarVisible15": {},
    "StarVisible16": {},
    "StarVisible17": {},
    "StarVisible18": {},
    "StarVisible19": {},
    "StarVisible2": {},
    "StarVisible20": {},
    "StarVisible21": {},
    "StarVisible22": {},
    "StarVisible23": {},
    "StarVisible24": {},
    "StarVisible25": {},
    "StarVisible26": {},
    "StarVisible27": {},
    "StarVisible28": {},
    "StarVisible29": {},
    "StarVisible3": {},
    "StarVisible30": {},
    "StarVisible31": {},
    "StarVisible32": {},
    "StarVisible33": {},
    "StarVisible34": {},
    "StarVisible35": {},
    "StarVisible36": {},
    "StarVisible37": {},
    "StarVisible38": {},
    "StarVisible39": {},
    "StarVisible4": {},
    "StarVisible40": {},
    "StarVisible41": {},
    "StarVisible42": {},
    "StarVisible43": {},
    "StarVisible44": {},
    "StarVisible45": {},
    "StarVisible46": {},
    "StarVisible47": {},
    "StarVisible5": {},
    "StarVisible50": {},
    "StarVisible50_1": {},
    "StarVisible52": {},
    "StarVisible52_1": {},
    "StarVisible53": {},
    "StarVisible53_1": {},
    "StarVisible54": {},
    "StarVisible54_1": {},
    "StarVisible55": {},
    "StarVisible55_1": {},
    "StarVisible56": {},
    "StarVisible56_1": {},
    "StarVisible57": {},
    "StarVisible57_1": {},
    "StarVisible58": {},
    "StarVisible58_1": {},
    "StarVisible59": {},
    "StarVisible59_1": {},
    "StarVisible6": {},
    "StarVisible60": {},
    "StarVisible60_1": {},
    "StarVisible61": {},
    "StarVisible61_1": {},
    "StarVisible62": {},
    "StarVisible62_1": {},
    "StarVisible63": {},
    "StarVisible63_1": {},
    "StarVisible64": {},
    "StarVisible64_1": {},
    "StarVisible68": {},
    "StarVisible68_1": {},
    "StarVisible69": {},
    "StarVisible69_1": {},
    "StarVisible7": {},
    "StarVisible70": {},
    "StarVisible70_1": {},
    "StarVisible71": {},
    "StarVisible71_1": {},
    "StarVisible72": {},
    "StarVisible72_1": {},
    "StarVisible8": {},
    "StarVisible86": {},
    "StarVisible89": {},
    "StarVisible89_1": {},
    "StarVisible9": {},
    "StarVisible90": {},
    "StarVisible90_1": {},
    "StarVisible91": {},
    "StarVisible91_1": {},
    "StarVisible92": {},
    "StarVisible92_1": {},
    "StarVisible93": {},
    "StarVisible93_1": {},
    "StarVisible94": {},
    "StarVisible94_1": {},
    "StarVisible95": {},
    "StarVisible95_1": {},
    "StarVisible96": {},
    "StarVisible96_1": {},
    "StarVisible97": {},
    "StarVisible97_1": {},
    "StarVisible98": {},
    "StarVisible98_1": {},
    "Stempelgeld_DataCard2": {},
    "Subtitle3": {},
    "Subtitle4": {},
    "Subtitle5": {},
    "Subtitle6": {},
    "Subtitle8": {},
    "Telefoon/Internet/TV_DataCard2": {},
    "Telefoon_DataCard4": {},
    "Telefoon_DataCard4_1": {},
    "Telefoonnummer_DataCard1": {},
    "TextInput1": {},
    "Title_DataCard4": {},
    "Title_DataCard4_1": {},
    "Title1": {},
    "Title4": {},
    "Title5": {},
    "Title6": {},
    "Title7": {},
    "Title9": {},
    "ToevoegenBezoekverslag": {},
    "ToevoegenKierbezoek": {},
    "ToevoegenWinkel": {},
    "Verantwoordelijke winkel_DataCard4": {},
    "Verantwoordelijke winkel_DataCard4_1": {},
    "Verslag_DataCard1": {},
    "Verslag_DataCard1_1": {},
    "Vervoerskosten_DataCard2": {},
    "Verzekeringen_DataCard2": {},
    "Volgende": {},
    "Volledige Naam_DataCard1": {},
    "Voor stuurgroep_DataCard1": {},
    "Voor stuurgroep_DataCard1_1": {},
    "Voornaam contact_DataCard1": {},
    "Voornaam_DataCard1": {},
    "Voornaam_DataCard2": {},
    "VrijdagOpen_DataCard1": {},
    "VrijdagOpen_DataCard1_1": {},
    "VrijdagSluiting_DataCard1": {},
    "VrijdagSluiting_DataCard1_1": {},
    "Water_DataCard2": {},
    "WijzigenBezoeksverslag": {},
    "WijzigenWinkel": {},
    "Winkelregel_DataCard4": {},
    "Winkelregel_DataCard4_1": {},
    "WinkelToevoegen": {},
    "WinkelToevoegen_1": {},
    "WoensdagOpen_DataCard1": {},
    "WoensdagOpen_DataCard1_1": {},
    "WoensdagSluiting_DataCard1": {},
    "WoensdagSluiting_DataCard1_1": {},
    "ZaterdagOpen_DataCard1": {},
    "ZaterdagOpen_DataCard1_1": {},
    "ZaterdagSluiting_DataCard1": {},
    "ZaterdagSluiting_DataCard1_1": {},
    "Ziekteuitkering_DataCard2": {},
    "ZondagOpen_DataCard1": {},
    "ZondagOpen_DataCard1_1": {},
    "ZondagSluiting_DataCard1": {},
    "ZondagSluiting_DataCard1_1": {}
  },
  "PCFDynamicSchemaForIRRetrievalEntry": {},
  "PublishOrderIndices": {
    "Actief_DataCard1": 98,
    "Actief_DataCard2": 751,
    "Adres_DataCard1": 33,
    "Adres_DataCard2": 721,
    "Adres_DataCard5": 437,
    "Adres_DataCard5_1": 561,
    "Afbetalingen_DataCard2": 197,
    "Afspraken_DataCard4": 477,
    "Afspraken_DataCard4_1": 601,
    "Alimentatieuit_DataCard2": 202,
    "Andere inkomsten_DataCard2": 137,
    "Andere uitgaven_DataCard2": 212,
    "App": 0,
    "Attachments_DataCard3": 313,
    "Bezoeker_DataCard2": 430,
    "Body1": 425,
    "Budgetmeter_DataCard2": 207,
    "Burgerlijke staat_DataCard1": 83,
    "Burgerlijke staat_DataCard2": 786,
    "Button1": 223,
    "Button1_1": 280,
    "Button1_2": 305,
    "Button1_3": 319,
    "Button10": 7,
    "Button11": 6,
    "Button12": 103,
    "Button13": 277,
    "Button13_1": 303,
    "Button14": 379,
    "Button14_1": 380,
    "Button14_2": 416,
    "Button14_3": 417,
    "Button15": 697,
    "Button15_1": 697,
    "Button15_4": 697,
    "Button15_5": 697,
    "Button2": 222,
    "Button2_1": 279,
    "Button2_2": 304,
    "Button2_3": 318,
    "Button3": 330,
    "Button4": 11,
    "Button5": 331,
    "Button6": 427,
    "Button6_1": 342,
    "Button7": 554,
    "Button7_1": 678,
    "Button8": 553,
    "Button8_1": 677,
    "Button9": 10,
    "ContactenScherm": 15,
    "Dakloos_DataCard1": 63,
    "Dakloos_DataCard2": 736,
    "DataCardKey1": 21,
    "DataCardKey10": 66,
    "DataCardKey100": 470,
    "DataCardKey100_1": 594,
    "DataCardKey101": 475,
    "DataCardKey101_1": 599,
    "DataCardKey102": 480,
    "DataCardKey102_1": 604,
    "DataCardKey11": 71,
    "DataCardKey115": 114,
    "DataCardKey116": 119,
    "DataCardKey117": 124,
    "DataCardKey118": 129,
    "DataCardKey119": 134,
    "DataCardKey12": 76,
    "DataCardKey120": 139,
    "DataCardKey122": 144,
    "DataCardKey123": 149,
    "DataCardKey124": 154,
    "DataCardKey125": 159,
    "DataCardKey126": 164,
    "DataCardKey127": 169,
    "DataCardKey128": 174,
    "DataCardKey129": 179,
    "DataCardKey13": 81,
    "DataCardKey130": 184,
    "DataCardKey131": 189,
    "DataCardKey132": 194,
    "DataCardKey133": 199,
    "DataCardKey134": 204,
    "DataCardKey135": 209,
    "DataCardKey136": 214,
    "DataCardKey139": 219,
    "DataCardKey14": 100,
    "DataCardKey15": 86,
    "DataCardKey16": 91,
    "DataCardKey17": 96,
    "DataCardKey18": 615,
    "DataCardKey19": 491,
    "DataCardKey2": 26,
    "DataCardKey20": 233,
    "DataCardKey21": 238,
    "DataCardKey22": 243,
    "DataCardKey23": 248,
    "DataCardKey24": 253,
    "DataCardKey25": 258,
    "DataCardKey26": 263,
    "DataCardKey27": 268,
    "DataCardKey28": 708,
    "DataCardKey29": 713,
    "DataCardKey3": 31,
    "DataCardKey30": 290,
    "DataCardKey31": 300,
    "DataCardKey32": 295,
    "DataCardKey33": 768,
    "DataCardKey34": 718,
    "DataCardKey35": 723,
    "DataCardKey36": 773,
    "DataCardKey37": 728,
    "DataCardKey38": 733,
    "DataCardKey39": 778,
    "DataCardKey4": 51,
    "DataCardKey40": 738,
    "DataCardKey41": 743,
    "DataCardKey42": 783,
    "DataCardKey43": 748,
    "DataCardKey44": 753,
    "DataCardKey45": 788,
    "DataCardKey46": 758,
    "DataCardKey47": 763,
    "DataCardKey48": 704,
    "DataCardKey5": 36,
    "DataCardKey50": 485,
    "DataCardKey50_1": 609,
    "DataCardKey52": 496,
    "DataCardKey52_1": 619,
    "DataCardKey53": 501,
    "DataCardKey53_1": 625,
    "DataCardKey54": 506,
    "DataCardKey54_1": 629,
    "DataCardKey55": 511,
    "DataCardKey55_1": 635,
    "DataCardKey56": 516,
    "DataCardKey56_1": 639,
    "DataCardKey57": 521,
    "DataCardKey57_1": 645,
    "DataCardKey58": 526,
    "DataCardKey58_1": 648,
    "DataCardKey59": 531,
    "DataCardKey59_1": 655,
    "DataCardKey6": 41,
    "DataCardKey60": 536,
    "DataCardKey60_1": 658,
    "DataCardKey61": 541,
    "DataCardKey61_1": 665,
    "DataCardKey62": 546,
    "DataCardKey62_1": 669,
    "DataCardKey63": 551,
    "DataCardKey63_1": 675,
    "DataCardKey67": 351,
    "DataCardKey67_1": 388,
    "DataCardKey7": 46,
    "DataCardKey71": 366,
    "DataCardKey71_1": 403,
    "DataCardKey72": 361,
    "DataCardKey72_1": 398,
    "DataCardKey73": 371,
    "DataCardKey73_1": 408,
    "DataCardKey74": 356,
    "DataCardKey74_1": 393,
    "DataCardKey75": 376,
    "DataCardKey75_1": 413,
    "DataCardKey8": 56,
    "DataCardKey9": 61,
    "DataCardKey90": 315,
    "DataCardKey93": 435,
    "DataCardKey93_1": 559,
    "DataCardKey94": 440,
    "DataCardKey94_1": 564,
    "DataCardKey95": 455,
    "DataCardKey95_1": 579,
    "DataCardKey96": 445,
    "DataCardKey96_1": 569,
    "DataCardKey97": 460,
    "DataCardKey97_1": 584,
    "DataCardKey98": 450,
    "DataCardKey98_1": 574,
    "DataCardKey99": 465,
    "DataCardKey99_1": 589,
    "DataCardValue1": 19,
    "DataCardValue10": 64,
    "DataCardValue100": 468,
    "DataCardValue100_1": 592,
    "DataCardValue101": 473,
    "DataCardValue101_1": 597,
    "DataCardValue102": 478,
    "DataCardValue102_1": 602,
    "DataCardValue11": 69,
    "DataCardValue115": 115,
    "DataCardValue116": 120,
    "DataCardValue117": 125,
    "DataCardValue118": 130,
    "DataCardValue119": 135,
    "DataCardValue12": 74,
    "DataCardValue120": 140,
    "DataCardValue122": 145,
    "DataCardValue123": 150,
    "DataCardValue124": 155,
    "DataCardValue125": 160,
    "DataCardValue126": 165,
    "DataCardValue127": 170,
    "DataCardValue128": 175,
    "DataCardValue129": 180,
    "DataCardValue13": 79,
    "DataCardValue130": 185,
    "DataCardValue131": 190,
    "DataCardValue132": 195,
    "DataCardValue133": 200,
    "DataCardValue134": 205,
    "DataCardValue135": 210,
    "DataCardValue136": 215,
    "DataCardValue139": 220,
    "DataCardValue14": 101,
    "DataCardValue15": 84,
    "DataCardValue16": 89,
    "DataCardValue17": 94,
    "DataCardValue18": 613,
    "DataCardValue19": 489,
    "DataCardValue2": 24,
    "DataCardValue20": 234,
    "DataCardValue21": 239,
    "DataCardValue22": 244,
    "DataCardValue23": 249,
    "DataCardValue24": 254,
    "DataCardValue25": 259,
    "DataCardValue26": 264,
    "DataCardValue27": 269,
    "DataCardValue28": 709,
    "DataCardValue29": 714,
    "DataCardValue3": 29,
    "DataCardValue30": 291,
    "DataCardValue31": 301,
    "DataCardValue32": 296,
    "DataCardValue33": 769,
    "DataCardValue34": 719,
    "DataCardValue35": 724,
    "DataCardValue36": 774,
    "DataCardValue37": 729,
    "DataCardValue38": 734,
    "DataCardValue39": 779,
    "DataCardValue4": 49,
    "DataCardValue40": 739,
    "DataCardValue41": 744,
    "DataCardValue42": 784,
    "DataCardValue43": 749,
    "DataCardValue44": 754,
    "DataCardValue45": 789,
    "DataCardValue46": 759,
    "DataCardValue47": 764,
    "DataCardValue48": 705,
    "DataCardValue5": 34,
    "DataCardValue50": 484,
    "DataCardValue50_1": 608,
    "DataCardValue52": 494,
    "DataCardValue52_1": 618,
    "DataCardValue53": 499,
    "DataCardValue53_1": 623,
    "DataCardValue54": 504,
    "DataCardValue54_1": 628,
    "DataCardValue55": 509,
    "DataCardValue55_1": 633,
    "DataCardValue56": 514,
    "DataCardValue56_1": 638,
    "DataCardValue57": 519,
    "DataCardValue57_1": 643,
    "DataCardValue58": 524,
    "DataCardValue58_1": 650,
    "DataCardValue59": 529,
    "DataCardValue59_1": 653,
    "DataCardValue6": 39,
    "DataCardValue60": 534,
    "DataCardValue60_1": 660,
    "DataCardValue61": 539,
    "DataCardValue61_1": 663,
    "DataCardValue62": 544,
    "DataCardValue62_1": 668,
    "DataCardValue63": 549,
    "DataCardValue63_1": 673,
    "DataCardValue67": 352,
    "DataCardValue67_1": 389,
    "DataCardValue7": 44,
    "DataCardValue71": 367,
    "DataCardValue71_1": 404,
    "DataCardValue72": 362,
    "DataCardValue72_1": 399,
    "DataCardValue73": 372,
    "DataCardValue73_1": 409,
    "DataCardValue74": 357,
    "DataCardValue74_1": 394,
    "DataCardValue75": 377,
    "DataCardValue75_1": 414,
    "DataCardValue8": 54,
    "DataCardValue9": 59,
    "DataCardValue90": 316,
    "DataCardValue93": 433,
    "DataCardValue93_1": 557,
    "DataCardValue94": 438,
    "DataCardValue94_1": 562,
    "DataCardValue95": 453,
    "DataCardValue95_1": 577,
    "DataCardValue96": 443,
    "DataCardValue96_1": 567,
    "DataCardValue97": 458,
    "DataCardValue97_1": 582,
    "DataCardValue98": 448,
    "DataCardValue98_1": 572,
    "DataCardValue99": 463,
    "DataCardValue99_1": 587,
    "Datum bezoek_DataCard1": 349,
    "Datum bezoek_DataCard1_1": 386,
    "Datum_DataCard1": 288,
    "DatumVandaag_1": 15,
    "DatumVandaag_10": 682,
    "DatumVandaag_11": 3,
    "DatumVandaag_12": 695,
    "DatumVandaag_2": 108,
    "DatumVandaag_3": 227,
    "DatumVandaag_4": 323,
    "DatumVandaag_5": 335,
    "DatumVandaag_6": 347,
    "DatumVandaag_7": 284,
    "DatumVandaag_8": 309,
    "DatumVandaag_9": 384,
    "DinsdagOpen_DataCard1": 493,
    "DinsdagOpen_DataCard1_1": 617,
    "DinsdagSluiting_DataCard1": 498,
    "DinsdagSluiting_DataCard1_1": 622,
    "DocumentenDossier": 15,
    "DonderdagOpen_DataCard1": 513,
    "DonderdagOpen_DataCard1_1": 637,
    "DonderdagSluiting_DataCard1": 518,
    "DonderdagSluiting_DataCard1_1": 642,
    "Elektriciteit_DataCard2": 157,
    "Email_DataCard1": 261,
    "ErrorMessage1": 22,
    "ErrorMessage10": 67,
    "ErrorMessage108": 116,
    "ErrorMessage109": 121,
    "ErrorMessage11": 72,
    "ErrorMessage110": 126,
    "ErrorMessage111": 131,
    "ErrorMessage112": 136,
    "ErrorMessage113": 141,
    "ErrorMessage114": 146,
    "ErrorMessage115": 151,
    "ErrorMessage116": 156,
    "ErrorMessage117": 161,
    "ErrorMessage118": 166,
    "ErrorMessage119": 171,
    "ErrorMessage12": 77,
    "ErrorMessage120": 176,
    "ErrorMessage121": 181,
    "ErrorMessage122": 186,
    "ErrorMessage123": 191,
    "ErrorMessage124": 196,
    "ErrorMessage125": 201,
    "ErrorMessage126": 206,
    "ErrorMessage127": 211,
    "ErrorMessage128": 216,
    "ErrorMessage129": 221,
    "ErrorMessage13": 82,
    "ErrorMessage14": 102,
    "ErrorMessage15": 87,
    "ErrorMessage16": 92,
    "ErrorMessage17": 97,
    "ErrorMessage18": 616,
    "ErrorMessage19": 235,
    "ErrorMessage2": 27,
    "ErrorMessage20": 240,
    "ErrorMessage21": 245,
    "ErrorMessage22": 250,
    "ErrorMessage23": 255,
    "ErrorMessage24": 260,
    "ErrorMessage25": 265,
    "ErrorMessage26": 270,
    "ErrorMessage27": 710,
    "ErrorMessage28": 715,
    "ErrorMessage29": 292,
    "ErrorMessage3": 32,
    "ErrorMessage30": 302,
    "ErrorMessage31": 297,
    "ErrorMessage32": 770,
    "ErrorMessage33": 720,
    "ErrorMessage34": 725,
    "ErrorMessage35": 775,
    "ErrorMessage36": 730,
    "ErrorMessage37": 735,
    "ErrorMessage38": 780,
    "ErrorMessage39": 740,
    "ErrorMessage4": 52,
    "ErrorMessage40": 745,
    "ErrorMessage41": 492,
    "ErrorMessage42": 785,
    "ErrorMessage43": 750,
    "ErrorMessage44": 755,
    "ErrorMessage45": 790,
    "ErrorMessage46": 760,
    "ErrorMessage47": 765,
    "ErrorMessage5": 37,
    "ErrorMessage50": 487,
    "ErrorMessage50_1": 611,
    "ErrorMessage52": 497,
    "ErrorMessage52_1": 621,
    "ErrorMessage53": 502,
    "ErrorMessage53_1": 626,
    "ErrorMessage54": 507,
    "ErrorMessage54_1": 631,
    "ErrorMessage55": 512,
    "ErrorMessage55_1": 636,
    "ErrorMessage56": 517,
    "ErrorMessage56_1": 641,
    "ErrorMessage57": 522,
    "ErrorMessage57_1": 646,
    "ErrorMessage58": 527,
    "ErrorMessage58_1": 651,
    "ErrorMessage59": 532,
    "ErrorMessage59_1": 656,
    "ErrorMessage6": 42,
    "ErrorMessage60": 537,
    "ErrorMessage60_1": 661,
    "ErrorMessage61": 542,
    "ErrorMessage61_1": 666,
    "ErrorMessage62": 547,
    "ErrorMessage62_1": 671,
    "ErrorMessage63": 552,
    "ErrorMessage63_1": 676,
    "ErrorMessage64": 353,
    "ErrorMessage64_1": 390,
    "ErrorMessage68": 368,
    "ErrorMessage68_1": 405,
    "ErrorMessage69": 363,
    "ErrorMessage69_1": 400,
    "ErrorMessage7": 47,
    "ErrorMessage70": 373,
    "ErrorMessage70_1": 410,
    "ErrorMessage71": 358,
    "ErrorMessage71_1": 395,
    "ErrorMessage72": 378,
    "ErrorMessage72_1": 415,
    "ErrorMessage8": 57,
    "ErrorMessage86": 317,
    "ErrorMessage89": 436,
    "ErrorMessage89_1": 560,
    "ErrorMessage9": 62,
    "ErrorMessage90": 441,
    "ErrorMessage90_1": 565,
    "ErrorMessage91": 456,
    "ErrorMessage91_1": 580,
    "ErrorMessage92": 446,
    "ErrorMessage92_1": 570,
    "ErrorMessage93": 461,
    "ErrorMessage93_1": 585,
    "ErrorMessage94": 451,
    "ErrorMessage94_1": 575,
    "ErrorMessage95": 466,
    "ErrorMessage95_1": 590,
    "ErrorMessage96": 471,
    "ErrorMessage96_1": 595,
    "ErrorMessage97": 476,
    "ErrorMessage97_1": 600,
    "ErrorMessage98": 481,
    "ErrorMessage98_1": 605,
    "EWG/MAAND_DataCard2": 147,
    "Familienaam contact_DataCard1": 241,
    "Financien": 15,
    "Form1": 702,
    "Form2": 429,
    "Form4": 312,
    "FormContact": 230,
    "FormFinanciën": 111,
    "FormOpeningsUren": 482,
    "FormOpeningsUren_1": 606,
    "FormPersoonGegevens": 17,
    "FormToevoegenVerslag": 348,
    "FormToevoegenWinkel": 431,
    "FormToevoegenWinkel_1": 555,
    "FormWijzigenVerslag": 385,
    "Gallery1": 324,
    "Gallery3": 336,
    "Gallery4": 271,
    "Gallery5": 420,
    "Gallery6": 686,
    "galleryTemplate1": 325,
    "galleryTemplate3": 337,
    "galleryTemplate4": 272,
    "galleryTemplate5": 687,
    "galleryTemplate6": 421,
    "Gas_DataCard2": 152,
    "Gast_DataCard1": 266,
    "Gast_DataCard2": 293,
    "Gast_DataCard4": 217,
    "Geboortedatum_DataCard1": 48,
    "Geboortedatum_DataCard2": 716,
    "Gelinkte dossiers_DataCard1": 93,
    "Gelinkte dossiers_DataCard2": 761,
    "Gemeente_DataCard1": 43,
    "Gemeente_DataCard2": 251,
    "Gemeente_DataCard3": 726,
    "Gemeente_DataCard5": 447,
    "Gemeente_DataCard5_1": 571,
    "Geslacht_DataCard1": 78,
    "Geslacht_DataCard2": 746,
    "Hoofdmenu": 2,
    "Hoofdmenu_1": 14,
    "Hoofdmenu_10": 681,
    "Hoofdmenu_11": 694,
    "Hoofdmenu_2": 107,
    "Hoofdmenu_3": 226,
    "Hoofdmenu_4": 322,
    "Hoofdmenu_5": 334,
    "Hoofdmenu_6": 346,
    "Hoofdmenu_7": 283,
    "Hoofdmenu_8": 308,
    "Hoofdmenu_9": 383,
    "Huur_DataCard2": 142,
    "Icon1": 278,
    "Icon3": 684,
    "Image4": 1,
    "Image4_1": 13,
    "Image4_10": 680,
    "Image4_11": 693,
    "Image4_2": 106,
    "Image4_3": 225,
    "Image4_4": 321,
    "Image4_5": 333,
    "Image4_6": 345,
    "Image4_7": 282,
    "Image4_8": 307,
    "Image4_9": 382,
    "Kennis Nederlands_DataCard1": 73,
    "Kennis Nederlands_DataCard2": 781,
    "Kierbezoeken": 143,
    "Kindergeld_DataCard2": 132,
    "Label1": 110,
    "Label1_1": 229,
    "Label1_2": 286,
    "Label1_3": 311,
    "Label2_1": 16,
    "Label2_2": 4,
    "Label2_3": 109,
    "Label2_4": 228,
    "Label2_5": 285,
    "Label2_6": 310,
    "Label2_7": 683,
    "Label2_8": 696,
    "Leefloon OCMW_DataCard2": 122,
    "LijstStuurgroep": 9,
    "Loon_DataCard2": 112,
    "MaandagOpen_DataCard1": 483,
    "MaandagOpen_DataCard1_1": 607,
    "MaandagSluiting_DataCard1": 488,
    "MaandagSluiting_DataCard2": 612,
    "Manier van aanmelden_DataCard1": 369,
    "Manier van aanmelden_DataCard1_1": 406,
    "Medische kosten_DataCard2": 187,
    "Moedertaal_DataCard1": 58,
    "Moedertaal_DataCard2": 776,
    "Mutualiteit_DataCard2": 182,
    "Naam bezoeker_DataCard1": 354,
    "Naam bezoeker_DataCard1_1": 391,
    "Naam_DataCard1": 18,
    "Naam_DataCard2": 706,
    "Nationaliteit_DataCard1": 53,
    "Nationaliteit_DataCard2": 731,
    "NextArrow3": 327,
    "NextArrow4": 424,
    "NextArrow5": 339,
    "NextArrow6": 274,
    "NextArrow8": 689,
    "NieuwBezoeksverlag": 8,
    "NieuwIntake": 5,
    "Nodige Informatie_DataCard4": 467,
    "Nodige Informatie_DataCard4_1": 591,
    "Omniostatuut_DataCard1": 68,
    "Omniostatuut_DataCard2": 741,
    "Opmerking_DataCard1": 298,
    "Opmerkingen_DataCard4": 472,
    "Opmerkingen_DataCard4_1": 596,
    "OpmerkingenDossier": 15,
    "OpmerkingsForm": 287,
    "OverzichtBezoekverslagen": 156,
    "OverzichtGasten": 0,
    "OverzichtPersoonGegevens": 0,
    "OverzichtWinkels": 169,
    "Permanentienaam_DataCard1": 364,
    "Permanentienaam_DataCard1_1": 401,
    "PersoonGegevens": 181,
    "Postcode_DataCard1": 38,
    "Postcode_DataCard2": 256,
    "Postcode_DataCard3": 771,
    "Postcode_DataCard5": 442,
    "Postcode_DataCard5_1": 566,
    "Rectangle1": 0,
    "Rectangle1_1": 12,
    "Rectangle1_10": 679,
    "Rectangle1_11": 692,
    "Rectangle1_2": 105,
    "Rectangle1_3": 224,
    "Rectangle1_4": 320,
    "Rectangle1_5": 332,
    "Rectangle1_6": 344,
    "Rectangle1_7": 281,
    "Rectangle1_8": 306,
    "Rectangle1_9": 381,
    "RectQuickActionBar1": 418,
    "Rijksregisternummer_DataCard1": 88,
    "Rijksregisternummer_DataCard2": 756,
    "Schoolgeld_DataCard2": 167,
    "Separator3": 329,
    "Separator4": 426,
    "Separator5": 341,
    "Separator6": 276,
    "Separator8": 691,
    "Soort contact_DataCard1": 231,
    "Soort gast_DataCard1": 28,
    "Soort gast_DataCard2": 766,
    "Startscherm": 274,
    "StarVisible1": 20,
    "StarVisible10": 65,
    "StarVisible108": 113,
    "StarVisible109": 118,
    "StarVisible11": 70,
    "StarVisible110": 123,
    "StarVisible111": 128,
    "StarVisible112": 133,
    "StarVisible113": 138,
    "StarVisible114": 143,
    "StarVisible115": 148,
    "StarVisible116": 153,
    "StarVisible117": 158,
    "StarVisible118": 163,
    "StarVisible119": 168,
    "StarVisible12": 75,
    "StarVisible120": 173,
    "StarVisible121": 178,
    "StarVisible122": 183,
    "StarVisible123": 188,
    "StarVisible124": 193,
    "StarVisible125": 198,
    "StarVisible126": 203,
    "StarVisible127": 208,
    "StarVisible128": 213,
    "StarVisible129": 218,
    "StarVisible13": 80,
    "StarVisible14": 99,
    "StarVisible15": 85,
    "StarVisible16": 90,
    "StarVisible17": 95,
    "StarVisible18": 614,
    "StarVisible19": 232,
    "StarVisible2": 25,
    "StarVisible20": 237,
    "StarVisible21": 242,
    "StarVisible22": 247,
    "StarVisible23": 252,
    "StarVisible24": 257,
    "StarVisible25": 262,
    "StarVisible26": 267,
    "StarVisible27": 707,
    "StarVisible28": 712,
    "StarVisible29": 289,
    "StarVisible3": 30,
    "StarVisible30": 299,
    "StarVisible31": 294,
    "StarVisible32": 767,
    "StarVisible33": 717,
    "StarVisible34": 722,
    "StarVisible35": 772,
    "StarVisible36": 727,
    "StarVisible37": 732,
    "StarVisible38": 777,
    "StarVisible39": 737,
    "StarVisible4": 50,
    "StarVisible40": 742,
    "StarVisible41": 490,
    "StarVisible42": 782,
    "StarVisible43": 747,
    "StarVisible44": 752,
    "StarVisible45": 787,
    "StarVisible46": 757,
    "StarVisible47": 762,
    "StarVisible5": 35,
    "StarVisible50": 486,
    "StarVisible50_1": 610,
    "StarVisible52": 495,
    "StarVisible52_1": 620,
    "StarVisible53": 500,
    "StarVisible53_1": 624,
    "StarVisible54": 505,
    "StarVisible54_1": 630,
    "StarVisible55": 510,
    "StarVisible55_1": 634,
    "StarVisible56": 515,
    "StarVisible56_1": 640,
    "StarVisible57": 520,
    "StarVisible57_1": 644,
    "StarVisible58": 525,
    "StarVisible58_1": 649,
    "StarVisible59": 530,
    "StarVisible59_1": 654,
    "StarVisible6": 40,
    "StarVisible60": 535,
    "StarVisible60_1": 659,
    "StarVisible61": 540,
    "StarVisible61_1": 664,
    "StarVisible62": 545,
    "StarVisible62_1": 670,
    "StarVisible63": 550,
    "StarVisible63_1": 674,
    "StarVisible64": 350,
    "StarVisible64_1": 387,
    "StarVisible68": 365,
    "StarVisible68_1": 402,
    "StarVisible69": 360,
    "StarVisible69_1": 397,
    "StarVisible7": 45,
    "StarVisible70": 370,
    "StarVisible70_1": 407,
    "StarVisible71": 355,
    "StarVisible71_1": 392,
    "StarVisible72": 375,
    "StarVisible72_1": 412,
    "StarVisible8": 55,
    "StarVisible86": 314,
    "StarVisible89": 434,
    "StarVisible89_1": 558,
    "StarVisible9": 60,
    "StarVisible90": 439,
    "StarVisible90_1": 563,
    "StarVisible91": 454,
    "StarVisible91_1": 578,
    "StarVisible92": 444,
    "StarVisible92_1": 568,
    "StarVisible93": 459,
    "StarVisible93_1": 583,
    "StarVisible94": 449,
    "StarVisible94_1": 573,
    "StarVisible95": 464,
    "StarVisible95_1": 588,
    "StarVisible96": 469,
    "StarVisible96_1": 593,
    "StarVisible97": 474,
    "StarVisible97_1": 598,
    "StarVisible98": 479,
    "StarVisible98_1": 603,
    "Stempelgeld_DataCard2": 117,
    "Subtitle3": 328,
    "Subtitle4": 423,
    "Subtitle5": 340,
    "Subtitle6": 275,
    "Subtitle8": 690,
    "Telefoon/Internet/TV_DataCard2": 172,
    "Telefoon_DataCard4": 452,
    "Telefoon_DataCard4_1": 576,
    "Telefoonnummer_DataCard1": 246,
    "TextInput1": 685,
    "Title_DataCard4": 432,
    "Title_DataCard4_1": 556,
    "Title1": 419,
    "Title4": 326,
    "Title5": 422,
    "Title6": 338,
    "Title7": 273,
    "Title9": 688,
    "ToevoegenBezoekverslag": 0,
    "ToevoegenKierbezoek": 294,
    "ToevoegenWinkel": 297,
    "Verantwoordelijke winkel_DataCard4": 457,
    "Verantwoordelijke winkel_DataCard4_1": 581,
    "Verslag_DataCard1": 374,
    "Verslag_DataCard1_1": 411,
    "Vervoerskosten_DataCard2": 177,
    "Verzekeringen_DataCard2": 192,
    "Volgende": 104,
    "Volledige Naam_DataCard1": 703,
    "Voor stuurgroep_DataCard1": 359,
    "Voor stuurgroep_DataCard1_1": 396,
    "Voornaam contact_DataCard1": 236,
    "Voornaam_DataCard1": 23,
    "Voornaam_DataCard2": 711,
    "VrijdagOpen_DataCard1": 523,
    "VrijdagOpen_DataCard1_1": 647,
    "VrijdagSluiting_DataCard1": 528,
    "VrijdagSluiting_DataCard1_1": 652,
    "Water_DataCard2": 162,
    "WijzigenBezoeksverslag": 0,
    "WijzigenWinkel": 460,
    "Winkelregel_DataCard4": 462,
    "Winkelregel_DataCard4_1": 586,
    "WinkelToevoegen": 428,
    "WinkelToevoegen_1": 343,
    "WoensdagOpen_DataCard1": 503,
    "WoensdagOpen_DataCard1_1": 627,
    "WoensdagSluiting_DataCard1": 508,
    "WoensdagSluiting_DataCard1_1": 632,
    "ZaterdagOpen_DataCard1": 533,
    "ZaterdagOpen_DataCard1_1": 657,
    "ZaterdagSluiting_DataCard1": 538,
    "ZaterdagSluiting_DataCard1_1": 662,
    "Ziekteuitkering_DataCard2": 127,
    "ZondagOpen_DataCard1": 543,
    "ZondagOpen_DataCard1_1": 667,
    "ZondagSluiting_DataCard1": 548,
    "ZondagSluiting_DataCard1_1": 672
  },
  "ResourcesJsonIndices": {
    "Image-MicrosoftTeams-image": 2,
    "Image-MicrosoftTeams-image (1)": 1,
    "Image-SampleImage": 0
  },
  "RuleScreenIdWithoutScreen": {},
  "TemplateVersions": {},
  "VolatileProperties": {
    "AnalysisLoadTime": 3.5536366,
    "ControlCount": {
      "attachments": 1,
      "button": 40,
      "combobox": 18,
      "datepicker": 4,
      "form": 12,
      "gallery": 5,
      "galleryTemplate": 5,
      "icon": 7,
      "image": 12,
      "label": 381,
      "rectangle": 18,
      "screen": 16,
      "text": 88,
      "toggleSwitch": 1,
      "typedDataCard": 112
    },
    "DeserializationLoadTime": 4.4875846,
    "ErrorCount": 15
  },
  "WasLocalDatabaseReferencesEmpty": true
}